scibeam/__init__.py
scibeam/core/__init__.py
scibeam/core/base.py
scibeam/core/common.py
scibeam/core/descriptor.py
scibeam/core/dictfunc.py
scibeam/core/formatter.py
scibeam/core/gaussian.py
scibeam/core/numerical.py
scibeam/core/peak.py
scibeam/core/plot.py
scibeam/core/regexp.py
scibeam/core/tofframe.py
scibeam/core/tofseries.py
scibeam/data/examples/time_series_1D/single_time_series.lvm
scibeam/data/examples/time_series_2D/20180314_APD1_0.30000in_scan.lvm
scibeam/data/examples/time_series_2D/20180314_APD1_0.32500in_scan.lvm
scibeam/data/examples/time_series_2D/20180314_APD1_0.35000in_scan.lvm
scibeam/data/examples/time_series_2D/20180314_APD1_0.37500in_scan.lvm
scibeam/data/examples/time_series_2D/20180314_APD1_0.40000in_scan.lvm
scibeam/data/examples/time_series_2D/20180314_APD1_0.42500in_scan.lvm
scibeam/data/examples/time_series_2D/20180314_APD1_0.45000in_scan.lvm
scibeam/data/examples/time_series_2D/20180314_APD1_0.47500in_scan.lvm
scibeam/data/examples/time_series_2D/20180314_APD1_0.50000in_scan.lvm
scibeam/data/examples/time_series_2D/20180314_APD1_0.52500in_scan.lvm
scibeam/data/examples/time_series_2D/20180314_APD1_0.55000in_scan.lvm
scibeam/data/examples/time_series_2D/20180314_APD1_0.57500in_scan.lvm
scibeam/data/examples/time_series_2D/20180314_APD1_0.60000in_scan.lvm
scibeam/data/examples/time_series_2D/20180314_APD1_0.62500in_scan.lvm
scibeam/data/examples/time_series_2D/20180314_APD1_0.65000in_scan.lvm
scibeam/data/examples/time_series_2D/20180314_APD1_0.67500in_scan.lvm
scibeam/data/examples/time_series_2D/20180314_APD1_0.70000in_scan.lvm
scibeam/data/examples/time_series_2D/20180314_APD1_0.72500in_scan.lvm
scibeam/data/examples/time_series_2D/20180314_APD1_0.75000in_scan.lvm
scibeam/data/examples/time_series_2D/20180314_APD1_0.77500in_scan.lvm
scibeam/data/examples/time_series_2D/20180314_APD1_0.80000in_scan.lvm
scibeam/data/examples/time_series_2D/20180314_APD1_0.82500in_scan.lvm
scibeam-0.1.1.dist-info/METADATA
scibeam-0.1.1.dist-info/RECORD
scibeam-0.1.1.dist-info/WHEEL
scibeam-0.1.1.dist-info/top_level.txt
