Metadata-Version: 2.1
Name: scibeam
Version: 0.1.1
Summary: Library for scientific time series dat aanalysis and visualization on beam measurement
Home-page: https://github.com/SuperYuLu/SciBeam
Author: Yu Lu
Author-email: yulu@utexas.edu
License: LICENSE.txt
Keywords: physics time-series data-analysis pandas
Platform: UNKNOWN
Classifier: Programming Language :: Python :: 3.6
Classifier: Development Status :: 3 - Alpha
Classifier: Intended Audience :: Science/Research
Classifier: Topic :: Scientific/Engineering :: Physics
Classifier: License :: OSI Approved :: MIT License
Requires-Dist: numpy
Requires-Dist: pandas
Requires-Dist: scipy
Requires-Dist: matplotlib
